LICENSE
README.md
setup.cfg
setup.py
Brain_OC.egg-info/PKG-INFO
Brain_OC.egg-info/SOURCES.txt
Brain_OC.egg-info/dependency_links.txt
Brain_OC.egg-info/entry_points.txt
Brain_OC.egg-info/requires.txt
Brain_OC.egg-info/top_level.txt
Brain_OC.egg-info/zip-safe
brain/__init__.py
brain/__main__.py
brain/access.py
brain/errors.py
brain/install.py
brain/records.py
brain/rest.py
brain/service.py
brain/users.py
brain/definitions/db_host.json
brain/definitions/group.json
brain/definitions/key.json
brain/definitions/permissions.json
brain/definitions/user.json
brain/upgrades/__init__.py
brain/upgrades/v1_0_1_v1_1_0.py
brain/upgrades/v1_1_0_v1_1_1.py