Metadata-Version: 2.1
Name: Brain-OC
Version: 1.1.5
Summary: Brain contains a service to manage users and permissions
Home-page: https://ouroboroscoding.com/body/brain
Author: Chris Nasr - Ouroboros Coding Inc.
Author-email: chris@ouroboroscoding.com
License: Custom
Project-URL: Documentation, https://ouroboroscoding.com/body/brain
Project-URL: Source, https://github.com/ouroboroscoding/brain
Project-URL: Tracker, https://github.com/ouroboroscoding/brain/issues
Keywords: rest,microservices
Requires-Python: >=3.10
License-File: LICENSE
